sankeyview/__init__.py
sankeyview/augment_view_graph.py
sankeyview/dataset.py
sankeyview/dummy_nodes.py
sankeyview/graph_to_sankey.py
sankeyview/hierarchy.py
sankeyview/jupyter.py
sankeyview/layered_graph.py
sankeyview/ordering.py
sankeyview/partition.py
sankeyview/results_graph.py
sankeyview/sankey_definition.py
sankeyview/sankey_view.py
sankeyview/save_sankey.py
sankeyview/sentinel.py
sankeyview/utils.py
sankeyview/view_graph.py
sankeyview-1.1.8.dist-info/LICENSE
sankeyview-1.1.8.dist-info/WHEEL
sankeyview-1.1.8.dist-info/METADATA
sankeyview-1.1.8.dist-info/RECORD
